[
  {
    "_id": {
      "$oid": "60fc4df6691b3a4b9366c1c4"
    },
    "notes": [],
    "figure": "60fc44ef459e5848c414ec87",
    "video": {
      "$oid": "60fc4cc7691b3a4b9366c19d"
    },
    "user": {
      "$oid": "60f8aa3557d219facdeb65b3"
    },
    "key": "users/ema-lee/2021-07-24T17-29-24.848Z_SampleVideo_1280x720_2mb.mp4",
    "createdAt": {
      "$date": "2021-07-24T17:29:26.143Z"
    },
    "updatedAt": {
      "$date": "2021-07-24T17:29:26.143Z"
    },
    "__v": 0
  },
  {
    "_id": {
      "$oid": "60fc4e06691b3a4b9366c1cf"
    },
    "notes": [],
    "figure": "60fc44ef459e5848c414ec87",
    "video": {
      "$oid": "60fc4cce691b3a4b9366c1a3"
    },
    "user": {
      "$oid": "60f8aa3557d219facdeb65b3"
    },
    "key": "users/ema-lee/2021-07-24T17-29-36.480Z_SampleVideo_1280x720_2mb.mp4",
    "createdAt": {
      "$date": "2021-07-24T17:29:42.265Z"
    },
    "updatedAt": {
      "$date": "2021-07-24T17:29:42.265Z"
    },
    "__v": 0
  },
  {
    "_id": {
      "$oid": "60fc4e09691b3a4b9366c1da"
    },
    "notes": [
      {
        "$oid": "60fc4e36691b3a4b9366c1e5"
      }
    ],
    "figure": "60fc44ef459e5848c414ec87",
    "video": {
      "$oid": "60fc4cd8691b3a4b9366c1a9"
    },
    "user": {
      "$oid": "60f8aa3557d219facdeb65b3"
    },
    "key": "users/ema-lee/2021-07-24T17-29-44.972Z_SampleVideo_1280x720_2mb.mp4",
    "createdAt": {
      "$date": "2021-07-24T17:29:45.497Z"
    },
    "updatedAt": {
      "$date": "2021-07-24T17:30:30.603Z"
    },
    "__v": 0
  }
]
